sneakpeek/__init__.py
sneakpeek/console.py
sneakpeek/server.py
sneakpeek/sneakpeek.py
sneakpeek-0.10.0.dist-info/LICENSE
sneakpeek-0.10.0.dist-info/METADATA
sneakpeek-0.10.0.dist-info/WHEEL
sneakpeek-0.10.0.dist-info/entry_points.txt
sneakpeek-0.10.0.dist-info/RECORD
