Metadata-Version: 2.1
Name: sneakpeek
Version: 0.10.0
Summary: A python module to generate link previews.
Home-page: https://github.com/codingcoffee/sneakpeek
License: MIT
Keywords: open-graph-protocol,ogp,twitter,twitter-cards,python,schema,link-preview
Author: Ameya Shenoy
Author-email: shenoy.ameya@gmail.com
Maintainer: Ameya Shenoy
Maintainer-email: shenoy.ameya@gmail.com
Requires-Python: >=3.8,<4.0
Classifier: Development Status :: 4 - Beta
Classifier: Intended Audience :: Developers
Classifier: License :: OSI Approved :: MIT License
Classifier: Operating System :: POSIX :: Linux
Classifier: Operating System :: Unix
Classifier: Programming Language :: Python :: 3
Classifier: Programming Language :: Python :: 3.8
Classifier: Programming Language :: Python :: 3.9
Classifier: Programming Language :: Python :: 3.10
Classifier: Programming Language :: Python :: 3.11
Classifier: Programming Language :: Python :: 3.12
Classifier: Programming Language :: Python :: 3.7
Classifier: Topic :: Software Development :: Build Tools
Classifier: Topic :: Software Development :: Libraries
Classifier: Topic :: Software Development :: Libraries :: Python Modules
Classifier: Topic :: Text Processing :: Markup :: HTML
Classifier: Topic :: Utilities
Requires-Dist: beautifulsoup4 (>=4.11.1,<5.0.0)
Requires-Dist: click (>=8.1.3,<9.0.0)
Requires-Dist: fastapi (==0.116.1)
Requires-Dist: loguru (>=0.7.0,<0.8.0)
Requires-Dist: rich (>=12.5.1,<13.0.0)
Requires-Dist: tweepy (>=4.10.0,<5.0.0)
Requires-Dist: uvicorn (>=0.18.2,<0.19.0)
Requires-Dist: validators (>=0.20.0,<0.21.0)
Requires-Dist: yt-dlp (>=2024.4.9,<2025.0.0)
Project-URL: Documentation, https://github.com/codingcoffee/sneakpeek
Project-URL: Repository, https://github.com/codingcoffee/sneakpeek
